seme/__init__.py
seme/__main__.py
seme/_http.py
seme/client.py
seme/exceptions.py
seme/api/__init__.py
seme/api/chat.py
seme/api/note.py
seme/api/user.py
seme/auth/__init__.py
seme/auth/api_key.py
seme/auth/oauth.py
seme/models/__init__.py
seme/models/auth.py
seme/models/chat.py
seme/models/note.py
seme/models/user.py
seme_sdk-0.1.2.dist-info/METADATA
seme_sdk-0.1.2.dist-info/WHEEL
seme_sdk-0.1.2.dist-info/entry_points.txt
seme_sdk-0.1.2.dist-info/licenses/LICENSE
seme_sdk-0.1.2.dist-info/RECORD
