Metadata-Version: 2.4
Name: seme-sdk
Version: 0.1.2
Summary: Python SDK for SecondMe API
Project-URL: Homepage, https://github.com/secondme/seme-sdk
Project-URL: Documentation, https://github.com/secondme/seme-sdk#readme
Project-URL: Repository, https://github.com/secondme/seme-sdk
Author: SecondMe Team
License-Expression: MIT
License-File: LICENSE
Keywords: ai,api,chat,sdk,secondme
Classifier: Development Status :: 4 - Beta
Classifier: Intended Audience :: Developers
Classifier: License :: OSI Approved :: MIT License
Classifier: Operating System :: OS Independent
Classifier: Programming Language :: Python :: 3
Classifier: Programming Language :: Python :: 3.8
Classifier: Programming Language :: Python :: 3.9
Classifier: Programming Language :: Python :: 3.10
Classifier: Programming Language :: Python :: 3.11
Classifier: Programming Language :: Python :: 3.12
Classifier: Typing :: Typed
Requires-Python: >=3.8
Requires-Dist: httpx>=0.25.0
Requires-Dist: pydantic>=2.0.0
Provides-Extra: dev
Requires-Dist: pytest>=7.0.0; extra == 'dev'
Requires-Dist: respx>=0.20.0; extra == 'dev'
Requires-Dist: ruff>=0.1.0; extra == 'dev'
